heisse_preise_data/__init__.py
heisse_preise_data-1.0.3.dist-info/LICENSE
heisse_preise_data-1.0.3.dist-info/METADATA
heisse_preise_data-1.0.3.dist-info/WHEEL
heisse_preise_data-1.0.3.dist-info/top_level.txt
heisse_preise_data-1.0.3.dist-info/RECORD
