Metadata-Version: 2.2
Name: heisse-preise-data
Version: 1.0.3
Summary: A Python package for downloading and extracting the data from heisse-preise.io with no dependencies.
Author-email: Dominik Falkner <falkner.dominik@gmail.com>
License: MIT License
Project-URL: Homepage, https://github.com/falknerdominik/heisse-preise-data
Project-URL: Documentation, https://github.com/falknerdominik/heisse-preise-data
Project-URL: Repository, https://github.com/falknerdominik/heisse-preise-data
Keywords: data,heisse-preise,daily-updated,compressed,data-package
Classifier: Development Status :: 5 - Production/Stable
Classifier: License :: OSI Approved :: MIT License
Classifier: Operating System :: OS Independent
Classifier: Programming Language :: Python :: 3
Classifier: Programming Language :: Python :: 3.7
Classifier: Programming Language :: Python :: 3.8
Classifier: Programming Language :: Python :: 3.9
Classifier: Programming Language :: Python :: 3.10
Classifier: Programming Language :: Python :: 3.11
Classifier: Programming Language :: Python :: 3.12
Classifier: Programming Language :: Python :: 3.13
Requires-Python: >=3.7
License-File: LICENSE
